setup.py
w3c_validator/__init__.py
w3c_validator/panels.py
w3c_validator/validator.py
w3c_validator.egg-info/PKG-INFO
w3c_validator.egg-info/SOURCES.txt
w3c_validator.egg-info/dependency_links.txt
w3c_validator.egg-info/requires.txt
w3c_validator.egg-info/top_level.txt
w3c_validator/templates/w3c_validator/panel.html