Metadata-Version: 1.0
Name: w3c-validator
Version: 0.1.0
Summary: W3C panel from Django Debug Toolbar using requests.
Home-page: https://bitbucket.org/amjoconn/w3c_validator
Author: Albert O'Connor
Author-email: iqc@albertoconnor.ca
License: UNKNOWN
Platform: UNKNOWN
Classifier: Development Status :: 4 - Beta
Classifier: Intended Audience :: Developers
Classifier: Natural Language :: English
Classifier: License :: OSI Approved :: MIT License
Classifier: Programming Language :: Python
Classifier: Programming Language :: Python :: 2.6
Classifier: Programming Language :: Python :: 2.7
